yatta/__init__.py
yatta/commands/__init__.py
yatta/commands/config.py
yatta/commands/delete.py
yatta/commands/edit.py
yatta/commands/list.py
yatta/commands/plot.py
yatta/commands/start.py
yatta/commands/timesheet.py
yatta/completion_helpers.py
yatta/config.py
yatta/console.py
yatta/daemon.py
yatta/db.py
yatta/plotting.py
yatta/utils.py
yatta-0.2.4.dist-info/entry_points.txt
yatta-0.2.4.dist-info/LICENSE
yatta-0.2.4.dist-info/WHEEL
yatta-0.2.4.dist-info/METADATA
yatta-0.2.4.dist-info/RECORD
